spacy_fastlang/__init__.py
spacy_fastlang/lid.176.ftz
spacy_fastlang-2.1.0.dist-info/LICENSE
spacy_fastlang-2.1.0.dist-info/METADATA
spacy_fastlang-2.1.0.dist-info/WHEEL
spacy_fastlang-2.1.0.dist-info/RECORD
