Metadata-Version: 2.1
Name: spacy_fastlang
Version: 2.1.0
Summary: Language detection using FastText and Spacy
Home-page: https://github.com/thomasthiebaud/spacy-fastlang
License: MIT
Keywords: spacy,fasttext,language,detection
Author: Thomas Thiebaud
Author-email: thiebaud.tom@gmail.com
Requires-Python: >=3.8,<4.0
Classifier: Development Status :: 4 - Beta
Classifier: Intended Audience :: Developers
Classifier: Intended Audience :: Science/Research
Classifier: License :: OSI Approved :: MIT License
Classifier: Operating System :: OS Independent
Classifier: Programming Language :: Python :: 3
Classifier: Programming Language :: Python :: 3.8
Classifier: Programming Language :: Python :: 3.9
Classifier: Programming Language :: Python :: 3.10
Classifier: Programming Language :: Python :: 3.11
Classifier: Programming Language :: Python :: 3.12
Classifier: Topic :: Scientific/Engineering
Classifier: Topic :: Software Development
Requires-Dist: fasttext-wheel (>=0.9.2,<0.10.0)
Requires-Dist: spacy (>=3.0.0,<4.0.0)
Project-URL: Documentation, https://github.com/thomasthiebaud/spacy-fastlang
Project-URL: Repository, https://github.com/thomasthiebaud/spacy-fastlang
